<annotation verified="yes">
	<folder>images</folder>
	<filename>csi_1600x1600_20180125_171741.jpg</filename>
	<path>F:\Temp\VM\LabelImage\images\csi_1600x1600_20180125_171741.jpg</path>
	<source>
		<database>Unknown</database>
	</source>
	<size>
		<width>1600</width>
		<height>1600</height>
		<depth>3</depth>
	</size>
	<segmented>0</segmented>
	<object>
		<name>chair</name>
		<pose>Unspecified</pose>
		<truncated>0</truncated>
		<difficult>0</difficult>
		<bndbox>
			<xmin>1067</xmin>
			<ymin>312</ymin>
			<xmax>1397</xmax>
			<ymax>582</ymax>
		</bndbox>
	</object>
	<object>
		<name>chair</name>
		<pose>Unspecified</pose>
		<truncated>0</truncated>
		<difficult>0</difficult>
		<bndbox>
			<xmin>1089</xmin>
			<ymin>1061</ymin>
			<xmax>1397</xmax>
			<ymax>1369</ymax>
		</bndbox>
	</object>
	<object>
		<name>sitting</name>
		<pose>Unspecified</pose>
		<truncated>0</truncated>
		<difficult>0</difficult>
		<bndbox>
			<xmin>83</xmin>
			<ymin>180</ymin>
			<xmax>527</xmax>
			<ymax>699</ymax>
		</bndbox>
	</object>
	<object>
		<name>sitting</name>
		<pose>Unspecified</pose>
		<truncated>0</truncated>
		<difficult>0</difficult>
		<bndbox>
			<xmin>129</xmin>
			<ymin>982</ymin>
			<xmax>516</xmax>
			<ymax>1436</ymax>
		</bndbox>
	</object>
</annotation>
