<annotation verified="yes">
	<folder>images</folder>
	<filename>csi_1600x1600_20180124_093739.jpg</filename>
	<path>F:\Temp\VM\LabelImage\images\csi_1600x1600_20180124_093739.jpg</path>
	<source>
		<database>Unknown</database>
	</source>
	<size>
		<width>1600</width>
		<height>1600</height>
		<depth>3</depth>
	</size>
	<segmented>0</segmented>
	<object>
		<name>standing</name>
		<pose>Unspecified</pose>
		<truncated>0</truncated>
		<difficult>0</difficult>
		<bndbox>
			<xmin>563</xmin>
			<ymin>471</ymin>
			<xmax>948</xmax>
			<ymax>858</ymax>
		</bndbox>
	</object>
	<object>
		<name>sitting</name>
		<pose>Unspecified</pose>
		<truncated>0</truncated>
		<difficult>0</difficult>
		<bndbox>
			<xmin>94</xmin>
			<ymin>347</ymin>
			<xmax>501</xmax>
			<ymax>747</ymax>
		</bndbox>
	</object>
	<object>
		<name>sitting</name>
		<pose>Unspecified</pose>
		<truncated>0</truncated>
		<difficult>0</difficult>
		<bndbox>
			<xmin>1008</xmin>
			<ymin>207</ymin>
			<xmax>1394</xmax>
			<ymax>611</ymax>
		</bndbox>
	</object>
	<object>
		<name>chair</name>
		<pose>Unspecified</pose>
		<truncated>0</truncated>
		<difficult>0</difficult>
		<bndbox>
			<xmin>194</xmin>
			<ymin>1120</ymin>
			<xmax>470</xmax>
			<ymax>1369</ymax>
		</bndbox>
	</object>
	<object>
		<name>chair</name>
		<pose>Unspecified</pose>
		<truncated>0</truncated>
		<difficult>0</difficult>
		<bndbox>
			<xmin>1088</xmin>
			<ymin>1098</ymin>
			<xmax>1348</xmax>
			<ymax>1402</ymax>
		</bndbox>
	</object>
</annotation>
