<annotation verified="yes">
	<folder>images</folder>
	<filename>csi_1600x1600_20180116_152004.jpg</filename>
	<path>F:\Temp\VM\LabelImage\images\csi_1600x1600_20180116_152004.jpg</path>
	<source>
		<database>Unknown</database>
	</source>
	<size>
		<width>1600</width>
		<height>1600</height>
		<depth>3</depth>
	</size>
	<segmented>0</segmented>
	<object>
		<name>sitting</name>
		<pose>Unspecified</pose>
		<truncated>0</truncated>
		<difficult>0</difficult>
		<bndbox>
			<xmin>1019</xmin>
			<ymin>231</ymin>
			<xmax>1403</xmax>
			<ymax>604</ymax>
		</bndbox>
	</object>
	<object>
		<name>sitting</name>
		<pose>Unspecified</pose>
		<truncated>0</truncated>
		<difficult>0</difficult>
		<bndbox>
			<xmin>174</xmin>
			<ymin>198</ymin>
			<xmax>630</xmax>
			<ymax>729</ymax>
		</bndbox>
	</object>
	<object>
		<name>sitting</name>
		<pose>Unspecified</pose>
		<truncated>0</truncated>
		<difficult>0</difficult>
		<bndbox>
			<xmin>172</xmin>
			<ymin>1091</ymin>
			<xmax>490</xmax>
			<ymax>1467</ymax>
		</bndbox>
	</object>
	<object>
		<name>chair</name>
		<pose>Unspecified</pose>
		<truncated>0</truncated>
		<difficult>0</difficult>
		<bndbox>
			<xmin>903</xmin>
			<ymin>913</ymin>
			<xmax>1279</xmax>
			<ymax>1209</ymax>
		</bndbox>
	</object>
</annotation>
